{
  "contracts": [
    {
      "trader": "trader/建投CTA一号",
      "vtSymbol": "PK2110.CZCE",
      "symbol": "PK110",
      "exchange": "CZCE",
      "product": "FUTURES",
      "name": "花生10月",
      "volumeMultiple": 5.0,
      "priceTick": 2.0,
      "expireDate": "2021-10-21",
      "startDeliveryDate": "2021-10-21",
      "longMarginRatio": 0.2,
      "shortMarginRatio": 0.2,
      "maxMarginSideAlgorithm": false,
      "commRate": {
        "trader": "trader/建投CTA一号",
        "vtSymbol": "",
        "symbol": "PK",
        "exchange": "",
        "openRatioByMoney": 0.0,
        "openRatioByVolume": 5.0,
        "closeRatioByMoney": 0.0,
        "closeRatioByVolume": 5.0,
        "closeTodayRatioByMoney": 0.0,
        "closeTodayRatioByVolume": 5.0
      },
      "orderCommRate": null
    },
    {
      "trader": "trader/建投CTA一号",
      "vtSymbol": "PK2111.CZCE",
      "symbol": "PK111",
      "exchange": "CZCE",
      "product": "FUTURES",
      "name": "花生11月",
      "volumeMultiple": 5.0,
      "priceTick": 2.0,
      "expireDate": "2021-11-12",
      "startDeliveryDate": "2021-11-12",
      "longMarginRatio": 0.2,
      "shortMarginRatio": 0.2,
      "maxMarginSideAlgorithm": false,
      "commRate": {
        "trader": "trader/建投CTA一号",
        "vtSymbol": "",
        "symbol": "PK",
        "exchange": "",
        "openRatioByMoney": 0.0,
        "openRatioByVolume": 5.0,
        "closeRatioByMoney": 0.0,
        "closeRatioByVolume": 5.0,
        "closeTodayRatioByMoney": 0.0,
        "closeTodayRatioByVolume": 5.0
      },
      "orderCommRate": null
    },
    {
      "trader": "trader/建投CTA一号",
      "vtSymbol": "PK2112.CZCE",
      "symbol": "PK112",
      "exchange": "CZCE",
      "product": "FUTURES",
      "name": "花生12月",
      "volumeMultiple": 5.0,
      "priceTick": 2.0,
      "expireDate": "2021-12-14",
      "startDeliveryDate": "2021-12-14",
      "longMarginRatio": 0.2,
      "shortMarginRatio": 0.2,
      "maxMarginSideAlgorithm": false,
      "commRate": {
        "trader": "trader/建投CTA一号",
        "vtSymbol": "",
        "symbol": "PK",
        "exchange": "",
        "openRatioByMoney": 0.0,
        "openRatioByVolume": 5.0,
        "closeRatioByMoney": 0.0,
        "closeRatioByVolume": 5.0,
        "closeTodayRatioByMoney": 0.0,
        "closeTodayRatioByVolume": 5.0
      },
      "orderCommRate": null
    },
    {
      "trader": "trader/建投CTA一号",
      "vtSymbol": "PK2201.CZCE",
      "symbol": "PK201",
      "exchange": "CZCE",
      "product": "FUTURES",
      "name": "花生1月",
      "volumeMultiple": 5.0,
      "priceTick": 2.0,
      "expireDate": "2022-01-17",
      "startDeliveryDate": "2022-01-17",
      "longMarginRatio": 0.2,
      "shortMarginRatio": 0.2,
      "maxMarginSideAlgorithm": false,
      "commRate": {
        "trader": "trader/建投CTA一号",
        "vtSymbol": "",
        "symbol": "PK",
        "exchange": "",
        "openRatioByMoney": 0.0,
        "openRatioByVolume": 5.0,
        "closeRatioByMoney": 0.0,
        "closeRatioByVolume": 5.0,
        "closeTodayRatioByMoney": 0.0,
        "closeTodayRatioByVolume": 5.0
      },
      "orderCommRate": null
    },
    {
      "trader": "trader/建投CTA一号",
      "vtSymbol": "PK2203.CZCE",
      "symbol": "PK203",
      "exchange": "CZCE",
      "product": "FUTURES",
      "name": "花生3月",
      "volumeMultiple": 5.0,
      "priceTick": 2.0,
      "expireDate": "2022-03-14",
      "startDeliveryDate": "2022-03-14",
      "longMarginRatio": 0.2,
      "shortMarginRatio": 0.2,
      "maxMarginSideAlgorithm": false,
      "commRate": {
        "trader": "trader/建投CTA一号",
        "vtSymbol": "",
        "symbol": "PK",
        "exchange": "",
        "openRatioByMoney": 0.0,
        "openRatioByVolume": 5.0,
        "closeRatioByMoney": 0.0,
        "closeRatioByVolume": 5.0,
        "closeTodayRatioByMoney": 0.0,
        "closeTodayRatioByVolume": 5.0
      },
      "orderCommRate": null
    },
    {
      "trader": "trader/建投CTA一号",
      "vtSymbol": "PK2204.CZCE",
      "symbol": "PK204",
      "exchange": "CZCE",
      "product": "FUTURES",
      "name": "花生4月",
      "volumeMultiple": 5.0,
      "priceTick": 2.0,
      "expireDate": "2022-04-18",
      "startDeliveryDate": "2022-04-18",
      "longMarginRatio": 0.2,
      "shortMarginRatio": 0.2,
      "maxMarginSideAlgorithm": false,
      "commRate": {
        "trader": "trader/建投CTA一号",
        "vtSymbol": "",
        "symbol": "PK",
        "exchange": "",
        "openRatioByMoney": 0.0,
        "openRatioByVolume": 5.0,
        "closeRatioByMoney": 0.0,
        "closeRatioByVolume": 5.0,
        "closeTodayRatioByMoney": 0.0,
        "closeTodayRatioByVolume": 5.0
      },
      "orderCommRate": null
    },
    {
      "trader": "trader/建投CTA一号",
      "vtSymbol": "PK2210.CZCE",
      "symbol": "PK210",
      "exchange": "CZCE",
      "product": "FUTURES",
      "name": "花生10月",
      "volumeMultiple": 5.0,
      "priceTick": 2.0,
      "expireDate": "2022-10-21",
      "startDeliveryDate": "2022-10-21",
      "longMarginRatio": 0.08,
      "shortMarginRatio": 0.08,
      "maxMarginSideAlgorithm": false,
      "commRate": {
        "trader": "trader/建投CTA一号",
        "vtSymbol": "",
        "symbol": "PK",
        "exchange": "",
        "openRatioByMoney": 0.0,
        "openRatioByVolume": 5.0,
        "closeRatioByMoney": 0.0,
        "closeRatioByVolume": 5.0,
        "closeTodayRatioByMoney": 0.0,
        "closeTodayRatioByVolume": 5.0
      },
      "orderCommRate": null
    },
    {
      "trader": "trader/建投CTA一号",
      "vtSymbol": "PK2211.CZCE",
      "symbol": "PK211",
      "exchange": "CZCE",
      "product": "FUTURES",
      "name": "花生11月",
      "volumeMultiple": 5.0,
      "priceTick": 2.0,
      "expireDate": "2022-11-14",
      "startDeliveryDate": "2022-11-14",
      "longMarginRatio": 0.08,
      "shortMarginRatio": 0.08,
      "maxMarginSideAlgorithm": false,
      "commRate": {
        "trader": "trader/建投CTA一号",
        "vtSymbol": "",
        "symbol": "PK",
        "exchange": "",
        "openRatioByMoney": 0.0,
        "openRatioByVolume": 5.0,
        "closeRatioByMoney": 0.0,
        "closeRatioByVolume": 5.0,
        "closeTodayRatioByMoney": 0.0,
        "closeTodayRatioByVolume": 5.0
      },
      "orderCommRate": null
    },
    {
      "trader": "trader/建投CTA一号",
      "vtSymbol": "PK2212.CZCE",
      "symbol": "PK212",
      "exchange": "CZCE",
      "product": "FUTURES",
      "name": "花生12月",
      "volumeMultiple": 5.0,
      "priceTick": 2.0,
      "expireDate": "2022-12-14",
      "startDeliveryDate": "2022-12-14",
      "longMarginRatio": 0.08,
      "shortMarginRatio": 0.08,
      "maxMarginSideAlgorithm": false,
      "commRate": {
        "trader": "trader/建投CTA一号",
        "vtSymbol": "",
        "symbol": "PK",
        "exchange": "",
        "openRatioByMoney": 0.0,
        "openRatioByVolume": 5.0,
        "closeRatioByMoney": 0.0,
        "closeRatioByVolume": 5.0,
        "closeTodayRatioByMoney": 0.0,
        "closeTodayRatioByVolume": 5.0
      },
      "orderCommRate": null
    },
    {
      "trader": "trader/建投CTA一号",
      "vtSymbol": "PK2301.CZCE",
      "symbol": "PK301",
      "exchange": "CZCE",
      "product": "FUTURES",
      "name": "花生1月",
      "volumeMultiple": 5.0,
      "priceTick": 2.0,
      "expireDate": "2023-01-13",
      "startDeliveryDate": "2023-01-13",
      "longMarginRatio": 0.08,
      "shortMarginRatio": 0.08,
      "maxMarginSideAlgorithm": false,
      "commRate": {
        "trader": "trader/建投CTA一号",
        "vtSymbol": "",
        "symbol": "PK",
        "exchange": "",
        "openRatioByMoney": 0.0,
        "openRatioByVolume": 5.0,
        "closeRatioByMoney": 0.0,
        "closeRatioByVolume": 5.0,
        "closeTodayRatioByMoney": 0.0,
        "closeTodayRatioByVolume": 5.0
      },
      "orderCommRate": null
    },
    {
      "trader": "trader/建投CTA一号",
      "vtSymbol": "PK2303.CZCE",
      "symbol": "PK303",
      "exchange": "CZCE",
      "product": "FUTURES",
      "name": "花生3月",
      "volumeMultiple": 5.0,
      "priceTick": 2.0,
      "expireDate": "2023-03-14",
      "startDeliveryDate": "2023-03-14",
      "longMarginRatio": 0.08,
      "shortMarginRatio": 0.08,
      "maxMarginSideAlgorithm": false,
      "commRate": {
        "trader": "trader/建投CTA一号",
        "vtSymbol": "",
        "symbol": "PK",
        "exchange": "",
        "openRatioByMoney": 0.0,
        "openRatioByVolume": 5.0,
        "closeRatioByMoney": 0.0,
        "closeRatioByVolume": 5.0,
        "closeTodayRatioByMoney": 0.0,
        "closeTodayRatioByVolume": 5.0
      },
      "orderCommRate": null
    }
  ]
}